genesiscreator/__init__.py
genesiscreator/__main__.py
genesiscreator/algorithms.py
genesiscreator/block.py
genesiscreator/cli.py
genesiscreator/constants.py
genesiscreator/transaction.py
genesiscreator-0.2.2.dist-info/DESCRIPTION.rst
genesiscreator-0.2.2.dist-info/METADATA
genesiscreator-0.2.2.dist-info/RECORD
genesiscreator-0.2.2.dist-info/WHEEL
genesiscreator-0.2.2.dist-info/entry_points.txt
genesiscreator-0.2.2.dist-info/metadata.json
genesiscreator-0.2.2.dist-info/top_level.txt
