Metadata-Version: 2.0
Name: genesiscreator
Version: 0.2.2
Summary: A Crypto-Currency Genesis Block Creator
Home-page: https://github.com/ahmedbodi/python-genesiscreator
Author: Ahmed Bodiwala
Author-email: ahmedbodi@multicoin.co
License: BSD 3-Clause License
Platform: UNKNOWN
Classifier: Development Status :: 5 - Production/Stable
Classifier: Intended Audience :: Developers
Classifier: License :: OSI Approved :: BSD License
Classifier: Operating System :: Unix
Classifier: Operating System :: POSIX
Classifier: Programming Language :: Python
Classifier: Programming Language :: Python :: 2.7
Classifier: Topic :: Utilities
Requires-Dist: construct (==2.5.2)
Requires-Dist: quark-hash (==1.0)
Requires-Dist: scrypt (==0.7.1)
Requires-Dist: x11-hash (==1.4)
